<?xml version="1.0" encoding="UTF-8"?>
<objects serializationModel="Studio.02.02.00">
	<object class="AudioFile" id="{55ccbc38-8136-481d-ba93-42024b7a3fef}">
		<property name="assetPath">
			<value>WoodBoxDrag_SFXB.1094.wav</value>
		</property>
		<property name="frequencyInKHz">
			<value>96</value>
		</property>
		<property name="channelCount">
			<value>2</value>
		</property>
		<property name="length">
			<value>2.5173333333333332</value>
		</property>
		<relationship name="masterAssetFolder">
			<destination>{79c8242f-fa14-4b1d-b6f9-24e34c9d3084}</destination>
		</relationship>
	</object>
</objects>
